{"id":116342,"name":"Carex eburnea","uploadedName":"Carex eburnea","slug":"carex-eburnea","reviewed":false,"reviewedThumbs":true,"reviewedImages":false,"taxa":{"genus":"Carex","species":"eburnea","ssp":"","v":"","x":false,"scientificAlts":[],"commonAlts":["Bristle-leaf Sedge","Bristleleaf Sedge","Bristle-leaved Sedge","Carex Ivoirin","Ivory Sedge"],"xparents":[],"commonName":"Ebony Sedge","scientificFamily":"Cyperaceae"},"needsReview":[],"thumb":{"1":[{"id":206398887,"idObsrv":121939764,"default":"https:inaturalist-open-data.s3.amazonaws.com/photos/206398887/medium.jpeg","fileType":"jpeg","width":2048,"height":1365,"credit":"(c) Quinten Wiegersma, some rights reserved (CC BY)","license":"cc-by","alt":"Carex eburnea","by":"Quinten Wiegersma","date":"2022-07-04","quality":"research"}],"2":[{"id":203526955,"idObsrv":120341647,"default":"https:inaturalist-open-data.s3.amazonaws.com/photos/203526955/medium.jpeg","fileType":"jpeg","width":1536,"height":2048,"credit":"no rights reserved","license":"cc0","alt":"Carex eburnea","by":"Étienne Lacroix-Carignan","date":"2022-07-04","quality":"research"}]},"images":[{"id":203520111,"idObsrv":120337996,"default":"https:inaturalist-open-data.s3.amazonaws.com/photos/203520111/medium.jpeg","fileType":"jpeg","width":1536,"height":2048,"credit":"no rights reserved","license":"cc0","alt":"Carex eburnea","by":"Étienne Lacroix-Carignan","date":"2022-07-04","quality":"research"}],"plantTypes":[],"lightNeeds":[],"growthHabit":[],"attracts":[],"tolerant":[],"uses":[],"problems":[],"soils":{"moistureNeeds":[],"types":[],"phNeeds":[]},"flowers":{"colors":[],"months":[],"seasons":[]},"leaves":{"retention":""},"fruits":{"colors":[],"months":[],"seasons":[]},"height":{"ranges":[],"unit":""},"spread":{"ranges":[],"unit":""},"ids":{"iNatId":116342,"natureServeId":131509,"usdaId":"CAEB2","mbgId":"279734"},"native":{"US":["NC","VT","IA","MO","MN","WI","TX","CT","WV","ME","VA","MT","MA","MD","KY","OH","MI","IN","AK","NH","IL","PA","NY","GA","AR","ND","AL","SC","TN","SD","NJ","WA","WY","NE"],"CA":["NF","MB","ON","NS","SK","NB","AB","NT","YT","BC","QC"]},"exotic":{},"regions":{},"status":[{"US:NC":"Critically Imperiled"},{"US:VT":"Secure but Declining"},{"US:IA":"Secure but Declining"},{"US:TX":"Critically Imperiled"},{"US:CT":"Vulnerable"},{"US:WV":"Vulnerable"},{"US:ME":"Critically Imperiled"},{"US:VA":"Secure but Declining"},{"US:MT":"Vulnerable"},{"US:MD":"Critically Imperiled"},{"US:KY":"Secure but Declining"},{"US:IN":"Vulnerable"},{"US:AK":"Vulnerable"},{"US:NH":"Critically Imperiled"},{"US:IL":"Vulnerable"},{"US:PA":"Critically Imperiled"},{"US:NY":"Secure but Declining"},{"US:GA":"Critically Imperiled"},{"US:AR":"Secure"},{"US:AL":"Imperiled"},{"US:SC":"Locally Extinct"},{"US:NJ":"Imperiled"},{"US:WA":"Critically Imperiled"},{"US:WY":"Critically Imperiled"},{"US:NE":"Secure but Declining"},{"CA:NF":"Vulnerable"},{"CA:MB":"Secure but Declining"},{"CA:ON":"Secure"},{"CA:NS":"Vulnerable"},{"CA:SK":"Vulnerable"},{"CA:NB":"Vulnerable"},{"CA:AB":"Secure but Declining"},{"CA:NT":"Secure but Declining"},{"CA:YT":"Secure but Declining"},{"CA:BC":"Secure"},{"CA:QC":"Secure but Declining"}],"externalLinks":[{"label":"Map (BONAP)","url":"http://bonap.net/MapGallery/County/carex eburnea.png"},{"label":"Vascular Plants of North Carolina","url":"https://auth1.dpr.ncparks.gov/flora/species_account.php?id=3004"},{"label":"Wikipedia","url":"http://en.wikipedia.org/wiki/Carex_eburnea"},{"label":"iNaturalist","url":"https://www.inaturalist.org/taxa/116342"},{"label":"NatureServe Explorer","url":"https://explorer.natureserve.org/Taxon/ELEMENT_GLOBAL.2.131509"},{"label":"Wildflower.org","url":"https://www.wildflower.org/plants/result.php?id_plant=CAEB2"},{"label":"USDA Plants Database","url":"https://plants.usda.gov/core/profile?symbol=CAEB2"},{"label":"Missouri Botanical Garden","url":"http://www.missouribotanicalgarden.org/PlantFinder/PlantFinderDetails.aspx?taxonid=279734"}],"sources":[{"label":"Vascular Plants of North Carolina","url":"https://auth1.dpr.ncparks.gov/flora/species_account.php?id=3004","from":"2022-07-01"},{"label":"iNaturalist","url":"https://www.inaturalist.org/taxa/116342","from":"2022-07-01"},{"label":"NatureServe","url":"https://explorer.natureserve.org/Taxon/ELEMENT_GLOBAL.2.131509","from":"2022-07-01"}]}