{"id":159640,"name":"Calamagrostis porteri","uploadedName":"Calamagrostis porteri","slug":"calamagrostis-porteri","reviewed":false,"reviewedThumbs":false,"reviewedImages":false,"taxa":{"genus":"Calamagrostis","species":"porteri","ssp":"","v":"","x":false,"scientificAlts":[],"commonAlts":[],"xparents":[],"commonName":"Porter's Reedgrass","scientificFamily":"Poaceae"},"needsReview":[],"thumb":{"1":[{"id":61288719,"idObsrv":38552275,"default":"https:inaturalist-open-data.s3.amazonaws.com/photos/61288719/medium.jpeg","fileType":"jpeg","width":1536,"height":2048,"credit":"(c) theo_witsell, some rights reserved (CC BY-NC)","license":"cc-by-nc","alt":"Calamagrostis porteri","by":"","date":"2022-07-05","quality":"research"}],"2":[{"id":23837031,"idObsrv":15932816,"default":"https:inaturalist-open-data.s3.amazonaws.com/photos/23837031/medium.jpg","fileType":"jpg","width":1536,"height":2048,"credit":"(c) Dwayne Estes, some rights reserved (CC BY-NC)","license":"cc-by-nc","alt":"Calamagrostis porteri","by":"Dwayne Estes","date":"2022-07-05","quality":"research"}]},"images":[{"id":20810406,"idObsrv":14061373,"default":"https:inaturalist-open-data.s3.amazonaws.com/photos/20810406/medium.jpg","fileType":"jpg","width":1536,"height":2048,"credit":"(c) theo_witsell, some rights reserved (CC BY-NC)","license":"cc-by-nc","alt":"Calamagrostis porteri","by":"","date":"2022-07-05","quality":"research"}],"plantTypes":[],"lightNeeds":[],"growthHabit":[],"attracts":[],"tolerant":[],"uses":[],"problems":[],"soils":{"moistureNeeds":[],"types":[],"phNeeds":[]},"flowers":{"colors":[],"months":[],"seasons":[]},"leaves":{"retention":""},"fruits":{"colors":[],"months":[],"seasons":[]},"height":{"ranges":[],"unit":""},"spread":{"ranges":[],"unit":""},"ids":{"iNatId":159640,"natureServeId":144509,"usdaId":"CAPO3"},"native":{"US":["VA","KY","NY","MO","WV","IL","GA","AR","MD","PA","IN","OH","NC","TN"]},"exotic":{},"regions":{},"status":[{"US:VA":"Secure but Declining"},{"US:WV":"Vulnerable"},{"US:GA":"Critically Imperiled"},{"US:MD":"Vulnerable"},{"US:PA":"Vulnerable"},{"US:NC":"Imperiled"},{"US:TN":"Critically Imperiled"}],"externalLinks":[{"label":"Map (BONAP)","url":"http://bonap.net/MapGallery/County/calamagrostis porteri.png"},{"label":"Vascular Plants of North Carolina","url":"https://auth1.dpr.ncparks.gov/flora/species_account.php?id=3731"},{"label":"iNaturalist","url":"https://www.inaturalist.org/taxa/159640"},{"label":"NatureServe Explorer","url":"https://explorer.natureserve.org/Taxon/ELEMENT_GLOBAL.2.144509"},{"label":"Wildflower.org","url":"https://www.wildflower.org/plants/result.php?id_plant=CAPO3"},{"label":"USDA Plants Database","url":"https://plants.usda.gov/core/profile?symbol=CAPO3"}],"sources":[{"label":"Vascular Plants of North Carolina","url":"https://auth1.dpr.ncparks.gov/flora/species_account.php?id=3731","from":"2022-07-01"},{"label":"iNaturalist","url":"https://www.inaturalist.org/taxa/159640","from":"2022-07-01"},{"label":"NatureServe","url":"https://explorer.natureserve.org/Taxon/ELEMENT_GLOBAL.2.144509","from":"2022-07-01"}]}