{"id":161508,"name":"Cyrilla racemiflora","uploadedName":"Cyrilla racemiflora","slug":"cyrilla-racemiflora","reviewed":false,"reviewedThumbs":true,"reviewedImages":true,"taxa":{"genus":"Cyrilla","species":"racemiflora","ssp":"","v":"","x":false,"scientificAlts":[],"commonAlts":["Titi","Swamp Cyrilla","Palo Colorado"],"xparents":[],"commonName":"Swamp Titi","scientificFamily":"Cyrillaceae","commonFamily":"Cyrilla"},"needsReview":[],"thumb":{"1":[{"id":77386075,"default":"https://inaturalist-open-data.s3.amazonaws.com/photos/77386075/medium.jpeg","fileType":"jpeg","credit":"no rights reserved","license":"cc0","alt":"Cyrilla racemiflora","by":"Jennifer Siegmann","date":"2020-07-17","width":1152,"height":2048,"idObsrv":48759938,"quality":"research"}],"2":[{"id":75033255,"default":"https://inaturalist-open-data.s3.amazonaws.com/photos/75033255/medium.jpeg","fileType":"jpeg","credit":"no rights reserved","license":"cc0","alt":"Cyrilla racemiflora","date":"2020-07-17","width":1536,"height":2048,"by":"","idObsrv":47313568,"quality":"research"}]},"images":[{"id":79341477,"credit":"(c) Ryan Watson, some rights reserved (CC BY)","license":"cc-by","alt":"Cyrilla racemiflora","date":"2020-07-01","default":"https://inaturalist-open-data.s3.amazonaws.com/photos/79341477/medium.jpeg","fileType":"jpeg","by":"Ryan Watson","width":2048,"height":1536,"idObsrv":49973159,"quality":"research"},{"id":79557625,"credit":"(c) Rob John, some rights reserved (CC BY)","license":"cc-by","alt":"Cyrilla racemiflora","date":"2020-07-01","default":"https://inaturalist-open-data.s3.amazonaws.com/photos/79557625/medium.jpeg","fileType":"jpeg","by":"Rob John","width":1536,"height":2048,"idObsrv":50102653,"quality":"research"},{"id":63822393,"credit":"(c) NC Wetlands, some rights reserved (CC BY)","license":"cc-by","alt":"Cyrilla racemiflora","date":"2020-07-01","default":"https://inaturalist-open-data.s3.amazonaws.com/photos/63822393/medium.jpeg","fileType":"jpeg","by":"NC Wetlands","width":1365,"height":2048,"idObsrv":40180080,"quality":"research"},{"id":29816589,"credit":"(c) Alison Northup, some rights reserved (CC BY)","license":"cc-by","alt":"Cyrilla racemiflora","date":"2020-07-01","default":"https://inaturalist-open-data.s3.amazonaws.com/photos/29816589/medium.jpeg","fileType":"jpeg","by":"Alison Northup","width":1536,"height":2048,"idObsrv":19386861,"quality":"needs_id"},{"id":80742564,"default":"https://inaturalist-open-data.s3.amazonaws.com/photos/80742564/medium.jpg","fileType":"jpg","credit":"no rights reserved","license":"cc0","alt":"Cyrilla racemiflora","by":"Becky","date":"2020-07-17","width":2048,"height":2048,"idObsrv":50836263,"quality":"needs_id"},{"id":80742496,"default":"https://inaturalist-open-data.s3.amazonaws.com/photos/80742496/medium.jpg","fileType":"jpg","credit":"no rights reserved","license":"cc0","alt":"Cyrilla racemiflora","by":"Becky","date":"2020-07-17","width":2048,"height":2048,"idObsrv":50836263,"quality":"needs_id"},{"id":80742763,"credit":"no rights reserved","license":"cc0","alt":"Cyrilla racemiflora","date":"2020-07-01","default":"https://inaturalist-open-data.s3.amazonaws.com/photos/80742763/medium.jpg","fileType":"jpg","by":"Becky","width":2048,"height":2048,"idObsrv":50836263,"quality":"needs_id"},{"id":74499304,"default":"https://inaturalist-open-data.s3.amazonaws.com/photos/74499304/medium.jpg","fileType":"jpg","credit":"(c) Farren Dell, some rights reserved (CC BY)","license":"cc-by","alt":"Cyrilla racemiflora","by":"Farren Dell","date":"2020-07-17","width":1536,"height":2048,"idObsrv":46976065,"quality":"research"},{"id":61870271,"default":"https://inaturalist-open-data.s3.amazonaws.com/photos/61870271/medium.jpg","fileType":"jpg","credit":"no rights reserved","license":"cc0","alt":"Cyrilla racemiflora","by":"Austin Pursley","date":"2020-07-17","width":1536,"height":2048,"idObsrv":38948329,"quality":"research"},{"id":40828381,"default":"https://inaturalist-open-data.s3.amazonaws.com/photos/40828381/medium.jpeg","fileType":"jpeg","credit":"(c) Jay Horn, some rights reserved (CC BY)","license":"cc-by","alt":"Cyrilla racemiflora","by":"Jay Horn","date":"2020-07-17","width":1152,"height":2048,"idObsrv":26300499,"quality":"research"},{"id":20578402,"default":"https://inaturalist-open-data.s3.amazonaws.com/photos/20578402/medium.jpg","fileType":"jpg","credit":"(c) Madison Gover, some rights reserved (CC BY)","license":"cc-by","alt":"Cyrilla racemiflora","by":"Madison Gover","date":"2020-07-17","width":1536,"height":2048,"idObsrv":13927774,"quality":"research"},{"id":19057707,"default":"https://inaturalist-open-data.s3.amazonaws.com/photos/19057707/medium.jpg","fileType":"jpg","credit":"(c) Melissa McMasters, some rights reserved (CC BY)","license":"cc-by","alt":"Cyrilla racemiflora","by":"Melissa McMasters","date":"2020-07-17","width":2048,"height":1365,"idObsrv":13082965,"quality":"research"}],"plantTypes":["Shrubs","Trees"],"lifeCycle":"Perennial","lightNeeds":["Sun","Part Shade"],"growthHabit":[],"gardens":true,"attracts":[],"tolerant":[],"uses":[],"problems":[],"soils":{"moistureNeeds":["Moist","Wet"],"types":[],"phNeeds":[]},"flowers":{"colors":["White"],"months":["5","6","7"],"seasons":["Spring","Summer"]},"leaves":{"retention":"Semi-Evergreen"},"fruits":{"colors":[],"months":[],"seasons":[]},"height":{"ranges":["12-36 ft."],"max":36,"min":12,"unit":"ft"},"spread":{"ranges":[],"unit":"ft"},"ids":{"iNatId":161508,"natureServeId":131680,"usdaId":"CYRA","trefleId":126627},"native":{"US":["GA","FL","TX","LA","AL","VA","SC","MS","NC"]},"exotic":{"US":["DE"]},"regions":{"US:NC":["Mountains","Piedmont","Coastal Plain"]},"status":[{"US:VA":"Vulnerable"},{"US:NC":"Secure"}],"externalLinks":[{"label":"North Carolina Native Plant Society","url":"https://ncwildflower.org/plant_galleries/details/cyrilla-racemiflora"},{"label":"Wikipedia","url":"http://en.wikipedia.org/wiki/Cyrilla"},{"label":"iNaturalist","url":"https://www.inaturalist.org/taxa/161508"},{"label":"NatureServe Explorer","url":"https://explorer.natureserve.org/Taxon/ELEMENT_GLOBAL.2.131680"},{"label":"Wildflower.org","url":"https://www.wildflower.org/plants/result.php?id_plant=CYRA"},{"label":"USDA Plants Database","url":"https://plants.usda.gov/core/profile?symbol=CYRA"},{"label":"North Carolina Extension Gardener Plant Toolbox","url":"https://plants.ces.ncsu.edu/plants/cyrilla-racemiflora"},{"label":"North Carolina Extension Gardener Plant Toolbox","url":"https://plants.ces.ncsu.edu/plants/cyrilla-racemiflora"}],"sources":[{"label":"North Carolina Native Plant Society","url":"https://ncwildflower.org/plant_galleries/details/cyrilla-racemiflora","from":"2020-07-05"},{"label":"iNaturalist","url":"https://www.inaturalist.org/taxa/161508","from":"2020-07-05"},{"label":"NatureServe Explorer","url":"https://explorer.natureserve.org/Taxon/ELEMENT_GLOBAL.2.131680","from":"2020-07-05"},{"label":"USDA Plants Database","url":"https://plants.usda.gov/core/profile?symbol=CYRA","from":"2020-07-05"}]}