{"id":163151,"name":"Galactia microphylla","uploadedName":"Galactia minor","slug":"galactia-microphylla","reviewed":false,"reviewedThumbs":true,"reviewedImages":false,"taxa":{"genus":"Galactia","species":"microphylla","ssp":"","v":"","x":false,"scientificAlts":["Galactia Regularis","Galactia minor"],"commonAlts":[],"xparents":[],"commonName":"Littleleaf Milkpea","scientificFamily":"Fabaceae"},"needsReview":[],"thumb":{"1":[{"id":76043246,"idObsrv":47936765,"default":"https:inaturalist-open-data.s3.amazonaws.com/photos/76043246/medium.jpeg","fileType":"jpeg","width":2048,"height":1536,"credit":"(c) Dr. Alison Northup, some rights reserved (CC BY)","license":"cc-by","alt":"Galactia microphylla","by":"Dr. Alison Northup","date":"2022-07-04","quality":"research"}],"2":[]},"images":[],"plantTypes":[],"lightNeeds":[],"growthHabit":[],"attracts":[],"tolerant":[],"uses":[],"problems":[],"soils":{"moistureNeeds":[],"types":[],"phNeeds":[]},"flowers":{"colors":[],"months":[],"seasons":[]},"leaves":{"retention":""},"fruits":{"colors":[],"months":[],"seasons":[]},"height":{"ranges":[],"unit":""},"spread":{"ranges":[],"unit":""},"ids":{"iNatId":163151,"natureServeId":130536},"native":{"US":["GA","MS","NC","SC","FL","AL"]},"exotic":{},"regions":{},"status":[{"US:GA":"Secure but Declining"},{"US:NC":"Imperiled"}],"externalLinks":[{"label":"Map (BONAP)","url":"http://bonap.net/MapGallery/County/galactia microphylla.png"},{"label":"Vascular Plants of North Carolina","url":"https://auth1.dpr.ncparks.gov/flora/species_account.php?id=1457"},{"label":"iNaturalist","url":"https://www.inaturalist.org/taxa/163151"},{"label":"NatureServe Explorer","url":"https://explorer.natureserve.org/Taxon/ELEMENT_GLOBAL.2.130536"},{"label":"North Carolina Extension Gardener Plant Toolbox","url":"https://plants.ces.ncsu.edu/plants/galactia-regularis"}],"sources":[{"label":"Vascular Plants of North Carolina","url":"https://auth1.dpr.ncparks.gov/flora/species_account.php?id=1457","from":"2022-07-01"},{"label":"iNaturalist","url":"https://www.inaturalist.org/taxa/163151","from":"2022-07-01"},{"label":"NatureServe","url":"https://explorer.natureserve.org/Taxon/ELEMENT_GLOBAL.2.130536","from":"2022-07-01"}]}