{"id":164282,"name":"Juncus subcaudatus","uploadedName":"Juncus subcaudatus","slug":"juncus-subcaudatus","reviewed":false,"reviewedThumbs":true,"reviewedImages":false,"taxa":{"genus":"Juncus","species":"subcaudatus","ssp":"","v":"","x":false,"scientificAlts":[],"commonAlts":["Jonc Subcaudé"],"xparents":[],"commonName":"Woodland Rush","scientificFamily":"Juncaceae"},"needsReview":[],"thumb":{"1":[{"id":185770852,"idObsrv":110152099,"default":"https:static.inaturalist.org/photos/185770852/medium.jpg","fileType":"jpg","width":1365,"height":2048,"credit":"(c) Nathan Aaron, some rights reserved (CC BY)","license":"cc-by","alt":"Juncus subcaudatus","by":"Nathan Aaron","date":"2022-07-04","quality":"research"}],"2":[{"id":19792998,"idObsrv":13479555,"default":"https:inaturalist-open-data.s3.amazonaws.com/photos/19792998/medium.jpg","fileType":"jpg","width":1536,"height":2048,"credit":"(c) Michael Ellis, some rights reserved (CC BY)","license":"cc-by","alt":"Juncus subcaudatus","by":"Michael Ellis","date":"2022-07-04","quality":"research"}]},"images":[],"plantTypes":[],"lightNeeds":[],"growthHabit":[],"attracts":[],"tolerant":[],"uses":[],"problems":[],"soils":{"moistureNeeds":[],"types":[],"phNeeds":[]},"flowers":{"colors":[],"months":[],"seasons":[]},"leaves":{"retention":""},"fruits":{"colors":[],"months":[],"seasons":[]},"height":{"ranges":[],"unit":""},"spread":{"ranges":[],"unit":""},"ids":{"iNatId":164282,"natureServeId":141664,"usdaId":"JUSU"},"native":{"CA":["NS","NF"],"US":["NJ","GA","OH","SC","NC","NY","MO","PA","MD","AR","MA","TN","CT","KY","DE","WV","VT","VA","DC"]},"exotic":{},"regions":{},"status":[{"CA:NS":"Vulnerable"},{"CA:NF":"Critically Imperiled"},{"US:OH":"Critically Imperiled"},{"US:SC":"Critically Imperiled"},{"US:NC":"Imperiled"},{"US:NY":"Critically Imperiled"},{"US:AR":"Critically Imperiled"},{"US:KY":"Critically Imperiled"},{"US:DE":"Critically Imperiled"},{"US:WV":"Secure but Declining"},{"US:VT":"Critically Imperiled"},{"US:VA":"Secure"}],"externalLinks":[{"label":"Map (BONAP)","url":"http://bonap.net/MapGallery/County/juncus subcaudatus.png"},{"label":"Vascular Plants of North Carolina","url":"https://auth1.dpr.ncparks.gov/flora/species_account.php?id=3402"},{"label":"iNaturalist","url":"https://www.inaturalist.org/taxa/164282"},{"label":"NatureServe Explorer","url":"https://explorer.natureserve.org/Taxon/ELEMENT_GLOBAL.2.141664"},{"label":"Wildflower.org","url":"https://www.wildflower.org/plants/result.php?id_plant=JUSU"},{"label":"USDA Plants Database","url":"https://plants.usda.gov/core/profile?symbol=JUSU"}],"sources":[{"label":"Vascular Plants of North Carolina","url":"https://auth1.dpr.ncparks.gov/flora/species_account.php?id=3402","from":"2022-07-01"},{"label":"iNaturalist","url":"https://www.inaturalist.org/taxa/164282","from":"2022-07-01"},{"label":"NatureServe","url":"https://explorer.natureserve.org/Taxon/ELEMENT_GLOBAL.2.141664","from":"2022-07-01"}]}