{"id":54839,"name":"Populus grandidentata","uploadedName":"Populus grandidentata","slug":"populus-grandidentata","reviewed":false,"reviewedThumbs":true,"reviewedImages":false,"taxa":{"genus":"Populus","species":"grandidentata","ssp":"","v":"","x":false,"scientificAlts":[],"commonAlts":["Large-tooth Aspen","Peuplier à Grandes Dents"],"xparents":[],"commonName":"Bigtooth Aspen","scientificFamily":"Salicaceae"},"needsReview":[],"thumb":{"1":[{"id":210887321,"idObsrv":124421433,"default":"https:inaturalist-open-data.s3.amazonaws.com/photos/210887321/medium.jpg","fileType":"jpg","width":1536,"height":2048,"credit":"(c) Jeff Clark, some rights reserved (CC BY)","license":"cc-by","alt":"Populus grandidentata","by":"Jeff Clark","date":"2022-07-05","quality":"research"}],"2":[{"id":209545750,"idObsrv":123678692,"default":"https:inaturalist-open-data.s3.amazonaws.com/photos/209545750/medium.jpeg","fileType":"jpeg","width":1536,"height":2048,"credit":"(c) John Baur, some rights reserved (CC BY)","license":"cc-by","alt":"Populus grandidentata","by":"John Baur","date":"2022-07-05","quality":"research"}]},"images":[{"id":207997269,"idObsrv":122831158,"default":"https:inaturalist-open-data.s3.amazonaws.com/photos/207997269/medium.jpeg","fileType":"jpeg","width":2048,"height":1536,"credit":"no rights reserved","license":"cc0","alt":"Populus grandidentata","by":"Lynn Harper","date":"2022-07-05","quality":"research"}],"plantTypes":[],"lightNeeds":[],"growthHabit":[],"attracts":[],"tolerant":[],"uses":[],"problems":[],"soils":{"moistureNeeds":[],"types":[],"phNeeds":[]},"flowers":{"colors":[],"months":[],"seasons":[]},"leaves":{"retention":""},"fruits":{"colors":[],"months":[],"seasons":[]},"height":{"ranges":[],"unit":""},"spread":{"ranges":[],"unit":""},"ids":{"iNatId":54839,"natureServeId":140795,"usdaId":"POGR4"},"native":{"US":["ME","MI","PA","MD","NJ","MO","MN","NC","DE","ND","DC","VT","WV","MA","IA","VA","NH","OH","WI","NY","RI","IL","KY","IN","TN","CT"],"CA":["PE","QC","NS","ON","NB","MB"]},"exotic":{"CA":["BC"]},"regions":{},"status":[{"US:PA":"Secure"},{"US:NJ":"Secure"},{"US:MO":"Critically Imperiled"},{"US:NC":"Imperiled"},{"US:DE":"Secure"},{"US:WV":"Secure"},{"US:IA":"Secure but Declining"},{"US:VA":"Secure"},{"US:NY":"Secure"},{"US:IL":"Secure but Declining"},{"US:KY":"Secure but Declining"},{"US:TN":"Imperiled"},{"CA:PE":"Secure"},{"CA:QC":"Secure"},{"CA:NS":"Secure"},{"CA:ON":"Secure"},{"CA:NB":"Secure"},{"CA:MB":"Critically Imperiled"}],"externalLinks":[{"label":"Map (BONAP)","url":"http://bonap.net/MapGallery/County/populus grandidentata.png"},{"label":"Vascular Plants of North Carolina","url":"https://auth1.dpr.ncparks.gov/flora/species_account.php?id=2519"},{"label":"Wikipedia","url":"http://en.wikipedia.org/wiki/Populus_grandidentata"},{"label":"iNaturalist","url":"https://www.inaturalist.org/taxa/54839"},{"label":"NatureServe Explorer","url":"https://explorer.natureserve.org/Taxon/ELEMENT_GLOBAL.2.140795"},{"label":"Wildflower.org","url":"https://www.wildflower.org/plants/result.php?id_plant=POGR4"},{"label":"USDA Plants Database","url":"https://plants.usda.gov/core/profile?symbol=POGR4"}],"sources":[{"label":"Vascular Plants of North Carolina","url":"https://auth1.dpr.ncparks.gov/flora/species_account.php?id=2519","from":"2022-07-01"},{"label":"iNaturalist","url":"https://www.inaturalist.org/taxa/54839","from":"2022-07-01"},{"label":"NatureServe","url":"https://explorer.natureserve.org/Taxon/ELEMENT_GLOBAL.2.140795","from":"2022-07-01"}]}