{"id":55402,"name":"Trillium grandiflorum","uploadedName":"Trillium grandiflorum","slug":"trillium-grandiflorum","reviewed":false,"reviewedThumbs":true,"reviewedImages":true,"taxa":{"genus":"Trillium","species":"grandiflorum","ssp":"","v":"","x":false,"scientificAlts":[],"commonAlts":["Large-flowered Trillium","White Trillium","Large-flower Trillium","Trille Blanc","Great White Trillium"],"xparents":[],"commonName":"Large White Trillium","scientificFamily":"Liliaceae","commonFamily":"Lily"},"needsReview":[],"thumb":{"1":[{"id":74570282,"idObsrv":47021322,"default":"https://inaturalist-open-data.s3.amazonaws.com/photos/74570282/medium.jpg","fileType":"jpg","width":1536,"height":2048,"credit":"no rights reserved","license":"cc0","alt":"Trillium grandiflorum","date":"2020-07-24","quality":"research"}],"2":[{"id":76595518,"idObsrv":48278912,"default":"https://inaturalist-open-data.s3.amazonaws.com/photos/76595518/medium.jpg","fileType":"jpg","width":1536,"height":2048,"credit":"(c) Andrew Sebastian, some rights reserved (CC BY)","license":"cc-by","alt":"Trillium grandiflorum","by":"Andrew Sebastian","date":"2020-07-24","quality":"research"}]},"images":[{"id":80741154,"idObsrv":50835462,"default":"https://inaturalist-open-data.s3.amazonaws.com/photos/80741154/medium.jpg","fileType":"jpg","width":1536,"height":2048,"credit":"(c) botany08, some rights reserved (CC BY)","license":"cc-by","alt":"Trillium grandiflorum","date":"2020-07-24","quality":"research"},{"id":75449123,"idObsrv":47569734,"default":"https://inaturalist-open-data.s3.amazonaws.com/photos/75449123/medium.jpg","fileType":"jpg","width":1536,"height":2048,"credit":"no rights reserved","license":"cc0","alt":"Trillium grandiflorum","by":"Dustin Minialoff","date":"2020-07-24","quality":"research"},{"id":76253097,"idObsrv":48069861,"default":"https://inaturalist-open-data.s3.amazonaws.com/photos/76253097/medium.jpg","fileType":"jpg","width":1536,"height":2048,"credit":"(c) Kristin Maling, some rights reserved (CC BY)","license":"cc-by","alt":"Trillium grandiflorum","by":"Kristin Maling","date":"2020-07-24","quality":"research"},{"id":75448921,"idObsrv":47569632,"default":"https://inaturalist-open-data.s3.amazonaws.com/photos/75448921/medium.jpg","fileType":"jpg","width":1536,"height":2048,"credit":"no rights reserved","license":"cc0","alt":"Trillium grandiflorum","by":"Dustin Minialoff","date":"2020-07-24","quality":"research"},{"id":75214578,"idObsrv":47423747,"default":"https://inaturalist-open-data.s3.amazonaws.com/photos/75214578/medium.jpg","fileType":"jpg","width":1152,"height":2048,"credit":"(c) Brad Von Blon, some rights reserved (CC BY-SA)","license":"cc-by-sa","alt":"Trillium grandiflorum","by":"Brad Von Blon","date":"2020-07-24","quality":"research"},{"id":74302338,"idObsrv":46852441,"default":"https://inaturalist-open-data.s3.amazonaws.com/photos/74302338/medium.jpg","fileType":"jpg","width":2048,"height":1536,"credit":"no rights reserved","license":"cc0","alt":"Trillium grandiflorum","by":"Peter Waycik","date":"2020-07-24","quality":"research"},{"id":74559996,"idObsrv":47015212,"default":"https://inaturalist-open-data.s3.amazonaws.com/photos/74559996/medium.jpg","fileType":"jpg","width":2048,"height":1536,"credit":"no rights reserved","license":"cc0","alt":"Trillium grandiflorum","date":"2020-07-24","quality":"research"},{"id":74164014,"idObsrv":46764069,"default":"https://inaturalist-open-data.s3.amazonaws.com/photos/74164014/medium.jpg","fileType":"jpg","width":1536,"height":2048,"credit":"(c) Summit Metro Parks, some rights reserved (CC BY-SA)","license":"cc-by-sa","alt":"Trillium grandiflorum","by":"Summit Metro Parks","date":"2020-07-24","quality":"research"},{"id":73904761,"idObsrv":46596339,"default":"https://inaturalist-open-data.s3.amazonaws.com/photos/73904761/medium.jpeg","fileType":"jpeg","width":2048,"height":1536,"credit":"no rights reserved","license":"cc0","alt":"Trillium grandiflorum","by":"Reuven Martin","date":"2020-07-24","quality":"research"},{"id":73802055,"idObsrv":46531675,"default":"https://inaturalist-open-data.s3.amazonaws.com/photos/73802055/medium.jpg","fileType":"jpg","width":1536,"height":2048,"credit":"no rights reserved","license":"cc0","alt":"Trillium grandiflorum","date":"2020-07-24","quality":"research"},{"id":73437388,"idObsrv":46303911,"default":"https://inaturalist-open-data.s3.amazonaws.com/photos/73437388/medium.jpeg","fileType":"jpeg","width":1536,"height":2048,"credit":"(c) stinger, some rights reserved (CC BY)","license":"cc-by","alt":"Trillium grandiflorum","date":"2020-07-24","quality":"research"},{"id":72518231,"idObsrv":45727062,"default":"https://inaturalist-open-data.s3.amazonaws.com/photos/72518231/medium.jpeg","fileType":"jpeg","width":2048,"height":1536,"credit":"no rights reserved","license":"cc0","alt":"Trillium grandiflorum","by":"Reuven Martin","date":"2020-07-24","quality":"research"},{"id":72520447,"idObsrv":45727756,"default":"https://inaturalist-open-data.s3.amazonaws.com/photos/72520447/medium.jpeg","fileType":"jpeg","width":1536,"height":2048,"credit":"(c) jpage_cwf, some rights reserved (CC BY-ND)","license":"cc-by-nd","alt":"Trillium grandiflorum","date":"2020-07-24","quality":"research"},{"id":70761839,"idObsrv":44634392,"default":"https://inaturalist-open-data.s3.amazonaws.com/photos/70761839/medium.jpg","fileType":"jpg","width":2048,"height":1365,"credit":"(c) Chris McAnlis, some rights reserved (CC BY)","license":"cc-by","alt":"Trillium grandiflorum","by":"Chris McAnlis","date":"2020-07-24","quality":"research"}],"plantTypes":["Wildflowers","Perennials"],"lifeCycle":"Perennial","lightNeeds":["Part Shade","Shade"],"growthHabit":[],"gardens":true,"attracts":[],"tolerant":[],"uses":[],"problems":[],"soils":{"moistureNeeds":["Moist"],"types":[],"phNeeds":[]},"flowers":{"colors":["White","Pink"],"months":["4","5"],"seasons":["Spring"]},"leaves":{"retention":"Deciduous"},"fruits":{"colors":[],"months":[],"seasons":[]},"height":{"ranges":["0-1 ft.","1-3 ft."],"max":3,"min":0,"unit":"ft"},"spread":{"ranges":[],"unit":"ft"},"ids":{"iNatId":55402,"natureServeId":152039,"usdaId":"TRGR4","mbgId":"281814","trefleId":189688},"native":{"CA":["NS","ON","NB","QC"],"US":["WV","NJ","WI","NC","IN","VT","GA","NH","VA","DC","OH","TN","PA","NY","MA","IL","MI","AL","CT","MN","SC","ME","MD","KY"]},"exotic":{"US":["DE"]},"regions":{"US:NC":["Mountains","Piedmont","Coastal Plain"]},"status":[{"CA:NS":"Critically Imperiled","US:IL":"Vulnerable"},{"CA:ON":"Secure","US:NC":"Secure"},{"CA:QC":"Vulnerable","US:GA":"Vulnerable"},{"US:WV":"Secure","US:VA":"Secure"},{"US:NJ":"Critically Imperiled","US:KY":"Secure but Declining"},{"US:NC":"Secure","US:NJ":"Critically Imperiled"},{"US:GA":"Vulnerable","US:NY":"Secure"},{"US:VA":"Secure","US:ME":"Likely Extinct"},{"US:NY":"Secure","US:SC":"Critically Imperiled"},{"US:IL":"Vulnerable","US:AL":"Critically Imperiled"},{"US:AL":"Critically Imperiled","US:WV":"Secure"},{"US:SC":"Critically Imperiled","CA:NS":"Critically Imperiled"},{"US:ME":"Likely Extinct","CA:ON":"Secure"},{"US:KY":"Secure but Declining","CA:QC":"Secure but Declining"}],"externalLinks":[{"label":"North Carolina Native Plant Society","url":"https://ncwildflower.org/plant_galleries/details/trillium-grandiflorum"},{"label":"Wikipedia","url":"http://en.wikipedia.org/wiki/Trillium_grandiflorum"},{"label":"iNaturalist","url":"https://www.inaturalist.org/taxa/55402"},{"label":"NatureServe Explorer","url":"https://explorer.natureserve.org/Taxon/ELEMENT_GLOBAL.2.152039"},{"label":"Wildflower.org","url":"https://www.wildflower.org/plants/result.php?id_plant=TRGR4"},{"label":"USDA Plants Database","url":"https://plants.usda.gov/core/profile?symbol=TRGR4"},{"label":"Missouri Botanical Garden","url":"http://www.missouribotanicalgarden.org/PlantFinder/PlantFinderDetails.aspx?taxonid=281814"},{"label":"North Carolina Extension Gardener Plant Toolbox","url":"https://plants.ces.ncsu.edu/plants/trillium-grandiflorum"},{"label":"North Carolina Extension Gardener Plant Toolbox","url":"https://plants.ces.ncsu.edu/plants/trillium-grandiflorum"}],"sources":[{"label":"North Carolina Native Plant Society","url":"https://ncwildflower.org/plant_galleries/details/trillium-grandiflorum","from":"2020-07-05"},{"label":"iNaturalist","url":"https://www.inaturalist.org/taxa/55402","from":"2020-07-05"},{"label":"NatureServe Explorer","url":"https://explorer.natureserve.org/Taxon/ELEMENT_GLOBAL.2.152039","from":"2020-07-05"},{"label":"USDA Plants Database","url":"https://plants.usda.gov/core/profile?symbol=TRGR4","from":"2020-07-05"}]}