{"id":75925,"name":"Calamagrostis canadensis","uploadedName":"Calamagrostis canadensis","slug":"calamagrostis-canadensis","reviewed":false,"reviewedThumbs":true,"reviewedImages":false,"taxa":{"genus":"Calamagrostis","species":"canadensis","ssp":"","v":"","x":false,"scientificAlts":[],"commonAlts":["Bluejoint Reedgrass","Blue-joint Reedgrass","Bluejoint","Calamagrostide du Canada","Canada Bluejoint"],"xparents":[],"commonName":"Canadian Bluejoint","scientificFamily":"Poaceae"},"needsReview":[],"thumb":{"1":[{"id":209152043,"idObsrv":123459930,"default":"https:inaturalist-open-data.s3.amazonaws.com/photos/209152043/medium.jpg","fileType":"jpg","width":1536,"height":2048,"credit":"(c) Andrew Sebastian, some rights reserved (CC BY)","license":"cc-by","alt":"Calamagrostis canadensis","by":"Andrew Sebastian","date":"2022-07-04","quality":"research"}],"2":[{"id":156257481,"idObsrv":94211443,"default":"https:inaturalist-open-data.s3.amazonaws.com/photos/156257481/medium.jpg","fileType":"jpg","width":2048,"height":1536,"credit":"(c) Matt Lavin, some rights reserved (CC BY-SA)","license":"cc-by-sa","alt":"Calamagrostis canadensis","by":"Matt Lavin","date":"2022-07-04","quality":"research"}]},"images":[{"id":156257471,"idObsrv":94211433,"default":"https:inaturalist-open-data.s3.amazonaws.com/photos/156257471/medium.jpg","fileType":"jpg","width":2048,"height":1536,"credit":"(c) Matt Lavin, some rights reserved (CC BY-SA)","license":"cc-by-sa","alt":"Calamagrostis canadensis","by":"Matt Lavin","date":"2022-07-04","quality":"research"}],"plantTypes":[],"lightNeeds":[],"growthHabit":[],"attracts":[],"tolerant":[],"uses":[],"problems":[],"soils":{"moistureNeeds":[],"types":[],"phNeeds":[]},"flowers":{"colors":[],"months":[],"seasons":[]},"leaves":{"retention":""},"fruits":{"colors":[],"months":[],"seasons":[]},"height":{"ranges":[],"unit":""},"spread":{"ranges":[],"unit":""},"ids":{"iNatId":75925,"natureServeId":143587,"usdaId":"CACA4"},"native":{"CA":["NF","AB","NS","QC","NB","NU","BC","NT","YT","ON","MB","SK","PE","LB"],"US":["WY","IL","MO","WA","KS","NV","MT","NY","PA","IN","MN","CA","VA","NM","TN","OH","VT","AK","ND","CO","WI","MI","WV","AZ","MA","NJ","IA","DE","RI","CT","KY","MD","ID","OR","ME","NE","SD","NC","NH","UT"]},"exotic":{},"regions":{},"status":[{"CA:NF":"Secure"},{"CA:AB":"Secure"},{"CA:NS":"Secure"},{"CA:NB":"Secure"},{"CA:NU":"Secure but Declining"},{"CA:BC":"Secure"},{"CA:NT":"Secure"},{"CA:YT":"Secure"},{"CA:ON":"Secure"},{"CA:MB":"Secure"},{"CA:SK":"Secure but Declining"},{"CA:PE":"Secure"},{"CA:LB":"Secure"},{"US:WY":"Secure but Declining"},{"US:IL":"Vulnerable"},{"US:KS":"Critically Imperiled"},{"US:MT":"Secure"},{"US:VA":"Secure but Declining"},{"US:VT":"Secure"},{"US:WV":"Secure but Declining"},{"US:IA":"Secure but Declining"},{"US:DE":"Critically Imperiled"},{"US:MD":"Secure but Declining"},{"US:NC":"Critically Imperiled"},{"US:NH":"Secure"}],"externalLinks":[{"label":"Map (BONAP)","url":"http://bonap.net/MapGallery/County/calamagrostis canadensis.png"},{"label":"Vascular Plants of North Carolina","url":"https://auth1.dpr.ncparks.gov/flora/species_account.php?id=3728"},{"label":"Wikipedia","url":"http://en.wikipedia.org/wiki/Calamagrostis_canadensis"},{"label":"iNaturalist","url":"https://www.inaturalist.org/taxa/75925"},{"label":"NatureServe Explorer","url":"https://explorer.natureserve.org/Taxon/ELEMENT_GLOBAL.2.143587"},{"label":"Wildflower.org","url":"https://www.wildflower.org/plants/result.php?id_plant=CACA4"},{"label":"USDA Plants Database","url":"https://plants.usda.gov/core/profile?symbol=CACA4"}],"sources":[{"label":"Vascular Plants of North Carolina","url":"https://auth1.dpr.ncparks.gov/flora/species_account.php?id=3728","from":"2022-07-01"},{"label":"iNaturalist","url":"https://www.inaturalist.org/taxa/75925","from":"2022-07-01"},{"label":"NatureServe","url":"https://explorer.natureserve.org/Taxon/ELEMENT_GLOBAL.2.143587","from":"2022-07-01"}]}