{"id":77549,"name":"Juncus acuminatus","uploadedName":"Juncus acuminatus","slug":"juncus-acuminatus","reviewed":false,"reviewedThumbs":true,"reviewedImages":false,"taxa":{"genus":"Juncus","species":"acuminatus","ssp":"","v":"","x":false,"scientificAlts":[],"commonAlts":["Tapertip Rush","Sharp-fruit Rush","Jonc à Tépales Acuminés"],"xparents":[],"commonName":"Tapered Rush","scientificFamily":"Juncaceae"},"needsReview":[],"thumb":{"1":[{"id":146228523,"idObsrv":88615306,"default":"https:static.inaturalist.org/photos/146228523/medium.jpg","fileType":"jpg","width":1536,"height":2048,"credit":"(c) John Michael, some rights reserved (CC BY)","license":"cc-by","alt":"Juncus acuminatus","by":"John Michael","date":"2022-07-04","quality":"research"}],"2":[{"id":135628623,"idObsrv":82625946,"default":"https:inaturalist-open-data.s3.amazonaws.com/photos/135628623/medium.jpg","fileType":"jpg","width":1536,"height":2048,"credit":"no rights reserved","license":"cc0","alt":"Juncus acuminatus","by":"John Kees","date":"2022-07-04","quality":"research"}]},"images":[{"id":105747114,"idObsrv":65676665,"default":"https:inaturalist-open-data.s3.amazonaws.com/photos/105747114/medium.jpeg","fileType":"jpeg","width":1536,"height":2048,"credit":"(c) Joe Potter Butler, some rights reserved (CC BY)","license":"cc-by","alt":"Juncus acuminatus","by":"Joe Potter Butler","date":"2022-07-04","quality":"research"}],"plantTypes":[],"lightNeeds":[],"growthHabit":[],"attracts":[],"tolerant":[],"uses":[],"problems":[],"soils":{"moistureNeeds":[],"types":[],"phNeeds":[]},"flowers":{"colors":[],"months":[],"seasons":[]},"leaves":{"retention":""},"fruits":{"colors":[],"months":[],"seasons":[]},"height":{"ranges":[],"unit":""},"spread":{"ranges":[],"unit":""},"ids":{"iNatId":77549,"natureServeId":158814,"usdaId":"JUAC"},"native":{"CA":["BC","NS","QC","ON"],"US":["TN","MD","AL","PA","NY","DC","KY","IA","FL","MA","MO","GA","RI","WI","OR","MS","LA","IN","DE","AR","WV","VT","NM","ME","AZ","NC","MI","VA","NH","OH","WA","ID","OK","SC","CA","MT","CT","IL","TX","KS","CO","NJ","NE"]},"exotic":{"US":["HI"]},"regions":{},"status":[{"CA:BC":"Secure"},{"CA:NS":"Vulnerable"},{"CA:QC":"Critically Imperiled"},{"CA:ON":"Vulnerable"},{"US:NY":"Secure"},{"US:KY":"Secure"},{"US:IA":"Secure but Declining"},{"US:DE":"Secure but Declining"},{"US:WV":"Secure"},{"US:VT":"Critically Imperiled"},{"US:NC":"Secure"},{"US:VA":"Secure"},{"US:MT":"Critically Imperiled"},{"US:IL":"Secure but Declining"},{"US:NJ":"Secure"},{"US:NE":"Critically Imperiled"}],"externalLinks":[{"label":"Map (BONAP)","url":"http://bonap.net/MapGallery/County/juncus acuminatus.png"},{"label":"Vascular Plants of North Carolina","url":"https://auth1.dpr.ncparks.gov/flora/species_account.php?id=3372"},{"label":"Wikipedia","url":"http://en.wikipedia.org/wiki/Juncus_acuminatus"},{"label":"iNaturalist","url":"https://www.inaturalist.org/taxa/77549"},{"label":"NatureServe Explorer","url":"https://explorer.natureserve.org/Taxon/ELEMENT_GLOBAL.2.158814"},{"label":"Wildflower.org","url":"https://www.wildflower.org/plants/result.php?id_plant=JUAC"},{"label":"USDA Plants Database","url":"https://plants.usda.gov/core/profile?symbol=JUAC"}],"sources":[{"label":"Vascular Plants of North Carolina","url":"https://auth1.dpr.ncparks.gov/flora/species_account.php?id=3372","from":"2022-07-01"},{"label":"iNaturalist","url":"https://www.inaturalist.org/taxa/77549","from":"2022-07-01"},{"label":"NatureServe","url":"https://explorer.natureserve.org/Taxon/ELEMENT_GLOBAL.2.158814","from":"2022-07-01"}]}