{"id":78650,"name":"Poa palustris","uploadedName":"Poa palustris","slug":"poa-palustris","reviewed":false,"reviewedThumbs":true,"reviewedImages":false,"taxa":{"genus":"Poa","species":"palustris","ssp":"","v":"","x":false,"scientificAlts":[],"commonAlts":["Fowl Bluegrass","Pâturin Des Marais"],"xparents":[],"commonName":"Swamp Meadow-grass","scientificFamily":"Poaceae"},"needsReview":[],"thumb":{"1":[{"id":210904791,"idObsrv":124431363,"default":"https:inaturalist-open-data.s3.amazonaws.com/photos/210904791/medium.jpg","fileType":"jpg","width":2048,"height":1536,"credit":"no rights reserved","license":"cc0","alt":"Poa palustris","by":"Tomas Pocius","date":"2022-07-05","quality":"research"}],"2":[{"id":207709760,"idObsrv":122665187,"default":"https:inaturalist-open-data.s3.amazonaws.com/photos/207709760/medium.jpeg","fileType":"jpeg","width":982,"height":2048,"credit":"(c) Yurii Basov, some rights reserved (CC BY)","license":"cc-by","alt":"Poa palustris","by":"Yurii Basov","date":"2022-07-05","quality":"research"}]},"images":[{"id":207393127,"idObsrv":122490516,"default":"https:inaturalist-open-data.s3.amazonaws.com/photos/207393127/medium.jpg","fileType":"jpg","width":287,"height":618,"credit":"(c) Георгий Виноградов (Georgy Vinogradov), some rights reserved (CC BY)","license":"cc-by","alt":"Poa palustris","by":"Георгий Виноградов (Georgy Vinogradov)","date":"2022-07-05","quality":"research"}],"plantTypes":[],"lightNeeds":[],"growthHabit":[],"attracts":[],"tolerant":[],"uses":[],"problems":[],"soils":{"moistureNeeds":[],"types":[],"phNeeds":[]},"flowers":{"colors":[],"months":[],"seasons":[]},"leaves":{"retention":""},"fruits":{"colors":[],"months":[],"seasons":[]},"height":{"ranges":[],"unit":""},"spread":{"ranges":[],"unit":""},"ids":{"iNatId":78650,"natureServeId":149461,"usdaId":"POPA2"},"native":{"CA":["NF","MB","NS","NB","SK","PE","NU","LB","AB","BC","QC","YT","NT","ON"],"US":["IN","ID","RI","VA","WY","SC","VT","IL","MO","OH","ND","DC","MI","WA","OR","NV","PA","SD","WI","AK","IA","MN","WV","NJ","CT","MA","NY","ME","AZ","CA","NC","NM","MD","NE","CO","UT","TN","NH"]},"exotic":{"US":["MT","DE"]},"regions":{},"status":[{"CA:NF":"Secure"},{"CA:MB":"Secure"},{"CA:NS":"Secure"},{"CA:NB":"Secure"},{"CA:SK":"Secure but Declining"},{"CA:PE":"Secure"},{"CA:NU":"Vulnerable"},{"CA:LB":"Secure but Declining"},{"CA:AB":"Secure"},{"CA:BC":"Secure"},{"CA:QC":"Secure"},{"CA:YT":"Secure"},{"CA:NT":"Secure but Declining"},{"CA:ON":"Secure"},{"US:VA":"Critically Imperiled"},{"US:WY":"Secure but Declining"},{"US:IL":"Vulnerable"},{"US:DC":"Likely Extinct"},{"US:IA":"Secure but Declining"},{"US:WV":"Secure but Declining"},{"US:NJ":"Secure but Declining"},{"US:NY":"Secure"},{"US:NC":"Critically Imperiled"},{"US:MD":"Critically Imperiled"},{"US:TN":"Critically Imperiled"}],"externalLinks":[{"label":"Map (BONAP)","url":"http://bonap.net/MapGallery/County/poa palustris.png"},{"label":"Vascular Plants of North Carolina","url":"https://auth1.dpr.ncparks.gov/flora/species_account.php?id=3964"},{"label":"Wikipedia","url":"http://en.wikipedia.org/wiki/Poa_palustris"},{"label":"iNaturalist","url":"https://www.inaturalist.org/taxa/78650"},{"label":"NatureServe Explorer","url":"https://explorer.natureserve.org/Taxon/ELEMENT_GLOBAL.2.149461"},{"label":"Wildflower.org","url":"https://www.wildflower.org/plants/result.php?id_plant=POPA2"},{"label":"USDA Plants Database","url":"https://plants.usda.gov/core/profile?symbol=POPA2"}],"sources":[{"label":"Vascular Plants of North Carolina","url":"https://auth1.dpr.ncparks.gov/flora/species_account.php?id=3964","from":"2022-07-01"},{"label":"iNaturalist","url":"https://www.inaturalist.org/taxa/78650","from":"2022-07-01"},{"label":"NatureServe","url":"https://explorer.natureserve.org/Taxon/ELEMENT_GLOBAL.2.149461","from":"2022-07-01"}]}