{"id":82569,"name":"Thelypteris palustris","uploadedName":"Thelypteris palustris","slug":"thelypteris-palustris","reviewed":false,"reviewedThumbs":true,"reviewedImages":false,"taxa":{"genus":"Thelypteris","species":"palustris","ssp":"","v":"","x":false,"scientificAlts":[],"commonAlts":["Eastern Marsh Fern","Thélyptère Des Marais"],"xparents":[],"commonName":"Marsh Fern","scientificFamily":"Thelypteridaceae"},"needsReview":[],"thumb":{"1":[{"id":211507689,"idObsrv":124768240,"default":"https:inaturalist-open-data.s3.amazonaws.com/photos/211507689/medium.jpg","fileType":"jpg","width":1152,"height":2048,"credit":"(c) loopy30, some rights reserved (CC BY-SA)","license":"cc-by-sa","alt":"Thelypteris palustris","by":"","date":"2022-07-05","quality":"research"}],"2":[{"id":211361785,"idObsrv":124684406,"default":"https:inaturalist-open-data.s3.amazonaws.com/photos/211361785/medium.jpeg","fileType":"jpeg","width":1367,"height":2048,"credit":"(c) marina_sad, some rights reserved (CC BY)","license":"cc-by","alt":"Thelypteris palustris","by":"","date":"2022-07-05","quality":"research"}]},"images":[{"id":210903260,"idObsrv":124430615,"default":"https:inaturalist-open-data.s3.amazonaws.com/photos/210903260/medium.jpg","fileType":"jpg","width":2048,"height":1536,"credit":"no rights reserved","license":"cc0","alt":"Thelypteris palustris","by":"Tomas Pocius","date":"2022-07-05","quality":"research"}],"plantTypes":[],"lightNeeds":[],"growthHabit":[],"attracts":[],"tolerant":[],"uses":[],"problems":[],"soils":{"moistureNeeds":[],"types":[],"phNeeds":[]},"flowers":{"colors":[],"months":[],"seasons":[]},"leaves":{"retention":""},"fruits":{"colors":[],"months":[],"seasons":[]},"height":{"ranges":[],"unit":""},"spread":{"ranges":[],"unit":""},"ids":{"iNatId":82569,"natureServeId":128026,"usdaId":"THPA"},"native":{"US":["MN","ME","MO","PA","OH","CT","MI","KY","IL","NY","IN","MA","RI","WI","NH","KS","AR","DE","SD","TX","TN","NC","IA","AL","VT","FL","VA","SC","OK","NE","WV","MS","GA","LA","NJ","DC","ND","MD"],"CA":["QC","PE","NS","SK","MB","NF","ON","NB"]},"exotic":{},"regions":{},"status":[{"US:NY":"Secure"},{"US:AR":"Vulnerable"},{"US:SD":"Critically Imperiled"},{"US:NC":"Secure"},{"US:IA":"Secure but Declining"},{"US:VA":"Secure"},{"US:WV":"Secure but Declining"},{"US:ND":"Vulnerable"},{"CA:PE":"Secure"},{"CA:NS":"Secure"},{"CA:SK":"Critically Imperiled"},{"CA:MB":"Vulnerable"},{"CA:NF":"Vulnerable"},{"CA:ON":"Secure"},{"CA:NB":"Secure"}],"externalLinks":[{"label":"Map (BONAP)","url":"http://bonap.net/MapGallery/County/thelypteris palustris.png"},{"label":"Vascular Plants of North Carolina","url":"https://auth1.dpr.ncparks.gov/flora/species_account.php?id=4250"},{"label":"Wikipedia","url":"http://en.wikipedia.org/wiki/Thelypteris_palustris"},{"label":"iNaturalist","url":"https://www.inaturalist.org/taxa/82569"},{"label":"NatureServe Explorer","url":"https://explorer.natureserve.org/Taxon/ELEMENT_GLOBAL.2.128026"},{"label":"Wildflower.org","url":"https://www.wildflower.org/plants/result.php?id_plant=THPA"},{"label":"USDA Plants Database","url":"https://plants.usda.gov/core/profile?symbol=THPA"}],"sources":[{"label":"Vascular Plants of North Carolina","url":"https://auth1.dpr.ncparks.gov/flora/species_account.php?id=4250","from":"2022-07-01"},{"label":"iNaturalist","url":"https://www.inaturalist.org/taxa/82569","from":"2022-07-01"},{"label":"NatureServe","url":"https://explorer.natureserve.org/Taxon/ELEMENT_GLOBAL.2.128026","from":"2022-07-01"}]}